jsontransform.py
json_transform-1.0.1.dist-info/METADATA
json_transform-1.0.1.dist-info/RECORD
json_transform-1.0.1.dist-info/WHEEL
json_transform-1.0.1.dist-info/top_level.txt
