Metadata-Version: 2.1
Name: json-transform
Version: 1.0.1
Summary: Convert python objects to JSON documents and vice versa.
Home-page: https://bitbucket.org/Peter-Morawski/json-transform
Author: Peter Morawski
Author-email: contact@peter-morawski.de
License: MIT License
Keywords: convert python object json
Platform: UNKNOWN
Classifier: Development Status :: 5 - Production/Stable
Classifier: Intended Audience :: Developers
Classifier: License :: OSI Approved :: MIT License
Classifier: Programming Language :: Python
Classifier: Programming Language :: Python :: 2.7
Classifier: Programming Language :: Python :: 3
Classifier: Programming Language :: Python :: 3.4
Classifier: Programming Language :: Python :: 3.5
Classifier: Programming Language :: Python :: 3.6
Classifier: Programming Language :: Python :: 3.7
Classifier: Operating System :: OS Independent
Classifier: Topic :: Communications
Classifier: Topic :: Software Development
Classifier: Topic :: Utilities
Requires-Dist: decorator (>=4.3.0)
Requires-Dist: python-dateutil (>=2.7.0)
